SekBot/__init__.py
SekBot-0.0.1.dist-info/METADATA
SekBot-0.0.1.dist-info/WHEEL
SekBot-0.0.1.dist-info/top_level.txt
SekBot-0.0.1.dist-info/RECORD
