Metadata-Version: 2.1
Name: SekBot
Version: 0.0.1
Summary: Sekkay's Tool For Launching More Than One Bot At Once!
Home-page: UNKNOWN
Author: Pirxcy
License: UNKNOWN
Platform: UNKNOWN
Classifier: Programming Language :: Python :: 3
Classifier: License :: OSI Approved :: MIT License
Classifier: Operating System :: OS Independent
Requires-Dist: aiohttp
